reclaim_sdk/__init__.py
reclaim_sdk/client.py
reclaim_sdk/exceptions.py
reclaim_sdk/resources/__init__.py
reclaim_sdk/resources/base.py
reclaim_sdk/resources/hours.py
reclaim_sdk/resources/task.py
reclaim_sdk-0.6.4.dist-info/licenses/LICENSE
reclaim_sdk-0.6.4.dist-info/METADATA
reclaim_sdk-0.6.4.dist-info/WHEEL
reclaim_sdk-0.6.4.dist-info/top_level.txt
reclaim_sdk-0.6.4.dist-info/RECORD
