Metadata-Version: 2.4
Name: reclaim-sdk
Version: 0.6.4
Summary: Unofficial Reclaim.ai Python API
Home-page: https://github.com/llabusch93/reclaim-sdk
Author: Laurence Lars Labusch
Author-email: lala@labiso.de
License: MIT
Project-URL: Bug Reports, https://github.com/llabusch93/reclaim-sdk/issues
Project-URL: Source, https://github.com/llabusch93/reclaim-sdk
Classifier: License :: OSI Approved :: MIT License
Classifier: Programming Language :: Python :: 3
Classifier: Programming Language :: Python :: 3.7
Classifier: Programming Language :: Python :: 3.8
Classifier: Programming Language :: Python :: 3.9
Classifier: Programming Language :: Python :: 3.10
Classifier: Programming Language :: Python :: 3.11
Requires-Python: >=3.7
License-File: LICENSE
Requires-Dist: httpx[http2]
Requires-Dist: python-dateutil
Requires-Dist: pydantic>=2.0.0
Provides-Extra: dev
Requires-Dist: flake8; extra == "dev"
Requires-Dist: black; extra == "dev"
Dynamic: author
Dynamic: author-email
Dynamic: classifier
Dynamic: description
Dynamic: description-content-type
Dynamic: home-page
Dynamic: license
Dynamic: license-file
Dynamic: project-url
Dynamic: provides-extra
Dynamic: requires-dist
Dynamic: requires-python
Dynamic: summary
